{
    "dynamics": {
        "navs": [
            "פרטים אישיים",
            "מדדים",
            "דף3"
        ],
        "/dynamics/page1": {
            "תאריך": "2024-06-20",
            "שם המועמד": "דניאל כץ",
            "שם המעריך": "אולגה",
            "title": "פרטים אישיים"
        },
        "/dynamics/page2": {
            "חוסן": "3",
            "שם המועמד": "",
            "שם המעריך": "",
            "title": "מדדים"
        }
    },
    "interview": {
        "navs": []
    },
    "interviewer survey": {
        "navs": []
    }
}